odoo/addons/product_uom_measure_type/README.rst
odoo/addons/product_uom_measure_type/__init__.py
odoo/addons/product_uom_measure_type/__manifest__.py
odoo/addons/product_uom_measure_type/hooks.py
odoo/addons/product_uom_measure_type/i18n/it.po
odoo/addons/product_uom_measure_type/i18n/product_uom_measure_type.pot
odoo/addons/product_uom_measure_type/models/__init__.py
odoo/addons/product_uom_measure_type/models/product_template.py
odoo/addons/product_uom_measure_type/readme/CONTRIBUTORS.rst
odoo/addons/product_uom_measure_type/readme/DESCRIPTION.rst
odoo/addons/product_uom_measure_type/readme/ROADMAP.rst
odoo/addons/product_uom_measure_type/static/description/icon.png
odoo/addons/product_uom_measure_type/static/description/index.html
odoo/addons/product_uom_measure_type/views/view_product_template.xml
odoo12_addon_product_uom_measure_type-12.0.1.0.1.99.dev6.dist-info/METADATA
odoo12_addon_product_uom_measure_type-12.0.1.0.1.99.dev6.dist-info/WHEEL
odoo12_addon_product_uom_measure_type-12.0.1.0.1.99.dev6.dist-info/top_level.txt
odoo12_addon_product_uom_measure_type-12.0.1.0.1.99.dev6.dist-info/RECORD
